docopt_sh/__init__.py
docopt_sh/__main__.py
docopt_sh/bash.py
docopt_sh/docopt.sh
docopt_sh/parser.py
docopt_sh/script.py
docopt_sh-2.0.3.dist-info/LICENSE
docopt_sh-2.0.3.dist-info/METADATA
docopt_sh-2.0.3.dist-info/WHEEL
docopt_sh-2.0.3.dist-info/entry_points.txt
docopt_sh-2.0.3.dist-info/RECORD
